Metadata-Version: 1.0
Name: TSAndrey-Server
Version: 0.0.1
Summary: Messanger_Server
Home-page: UNKNOWN
Author: Timborevich Andrey
Author-email: siblp@mail.ru
License: UNKNOWN
Platform: UNKNOWN
